replitdb/__init__.py
replitdb/__main__.py
replitdb/_async.py
replitdb/commands.py
replitdb/json_test.py
replitdb-0.0.15.dist-info/LICENSE
replitdb-0.0.15.dist-info/METADATA
replitdb-0.0.15.dist-info/WHEEL
replitdb-0.0.15.dist-info/entry_points.txt
replitdb-0.0.15.dist-info/top_level.txt
replitdb-0.0.15.dist-info/RECORD
