Metadata-Version: 2.1
Name: replitdb
Version: 0.0.15
Summary: a client for replit db
Home-page: https://github.com/Codemonkey51/replit-db-client
Author: codemonkey51
Author-email: pypi@codemonkey51.dev
License: UNKNOWN
Platform: UNKNOWN
Classifier: Programming Language :: Python :: 3
Classifier: License :: OSI Approved :: MIT License
Classifier: Operating System :: OS Independent
Requires-Python: >=3.6
Requires-Dist: requests-async
